opstrat_backtester/__init__.py
opstrat_backtester/api_client.py
opstrat_backtester/cache_manager.py
opstrat_backtester/data_loader.py
opstrat_backtester/analytics/__init__.py
opstrat_backtester/analytics/plots.py
opstrat_backtester/analytics/stats.py
opstrat_backtester/core/__init__.py
opstrat_backtester/core/engine.py
opstrat_backtester/core/events.py
opstrat_backtester/core/portfolio.py
opstrat_backtester/core/strategy.py
opstrat_backtester/data/datasource.py
opstrat_backtester-0.1.1.dist-info/METADATA
opstrat_backtester-0.1.1.dist-info/WHEEL
opstrat_backtester-0.1.1.dist-info/top_level.txt
opstrat_backtester-0.1.1.dist-info/RECORD
