Metadata-Version: 2.4
Name: opstrat_backtester
Version: 0.1.1
Summary: Options strategy backtesting library
Author-email: Plinio Zanini <pliniozanini@hotmail.com>
Project-URL: Homepage, https://github.com/pliniozanini/optstrat_bt
Project-URL: Issues, https://github.com/pliniozanini/optstrat_bt/issues
Classifier: Programming Language :: Python :: 3
Classifier: License :: OSI Approved :: MIT License
Classifier: Operating System :: OS Independent
Requires-Python: >=3.10
Requires-Dist: pandas
Requires-Dist: numpy
Requires-Dist: matplotlib
Requires-Dist: tqdm
Requires-Dist: requests
Requires-Dist: pyarrow
Requires-Dist: python-dotenv
Provides-Extra: dev
Requires-Dist: pytest>=7.4.2; extra == "dev"
Requires-Dist: pytest-mock>=3.11.1; extra == "dev"
